panoramacli/__init__.py
panoramacli/resources/Dockerfile
panoramacli/resources/__init__.py
panoramacli/resources/build_package.json
panoramacli/resources/camera_package.json
panoramacli/resources/datasink_package.json
panoramacli/resources/descriptor_container_template.json
panoramacli/resources/descriptor_model_template.json
panoramacli/resources/download_model.json
panoramacli/resources/graph_node_template.json
panoramacli/resources/graph_template.json
panoramacli/resources/package_interface_template.json
panoramacli/resources/package_template.json
panoramacli-1.1.6.data/scripts/panorama-cli
panoramacli-1.1.6.dist-info/LICENSE
panoramacli-1.1.6.dist-info/METADATA
panoramacli-1.1.6.dist-info/NOTICE
panoramacli-1.1.6.dist-info/WHEEL
panoramacli-1.1.6.dist-info/top_level.txt
panoramacli-1.1.6.dist-info/RECORD
