Metadata-Version: 2.1
Name: panoramacli
Version: 1.1.6
Summary: Panorama CLI
Home-page: https://github.com/aws/aws-panorama-cli
Author: AWS Panorama
License: Apache License 2.0
Keywords: aws panorama
Platform: UNKNOWN
Classifier: Development Status :: 5 - Production/Stable
Classifier: Intended Audience :: Developers
Classifier: License :: OSI Approved :: Apache Software License
Classifier: Programming Language :: Python
Classifier: Programming Language :: Python :: 3
Classifier: Programming Language :: Python :: 3.6
Classifier: Programming Language :: Python :: 3.7
Classifier: Programming Language :: Python :: 3.8
Classifier: Programming Language :: Python :: 3.9
Classifier: Programming Language :: Python :: 3.10
Classifier: Programming Language :: Python :: 3.11
Requires-Python: >=3.6
License-File: LICENSE
License-File: NOTICE
Requires-Dist: setuptools
